django_rename_table/__init__.py
django_rename_table/operations.py
django_rename_table-0.1.3.dist-info/LICENSE
django_rename_table-0.1.3.dist-info/METADATA
django_rename_table-0.1.3.dist-info/WHEEL
django_rename_table-0.1.3.dist-info/RECORD
