Metadata-Version: 2.1
Name: django-rename-table
Version: 0.1.3
Summary: Django migration operations for renaming tables with aliases and managing view aliases.
Home-page: https://github.com/mathewpower/django-rename-table
License: MIT
Keywords: django,migration,operations,database,postgresql
Author: Mathew Power
Author-email: mathew.power@gmail.com
Requires-Python: >=3.8,<3.14
Classifier: Development Status :: 2 - Pre-Alpha
Classifier: Framework :: Django
Classifier: Framework :: Django :: 3.2
Classifier: Framework :: Django :: 4.0
Classifier: Framework :: Django :: 4.1
Classifier: Framework :: Django :: 4.2
Classifier: Framework :: Django :: 5.0
Classifier: Framework :: Django :: 5.1
Classifier: License :: OSI Approved :: MIT License
Classifier: Operating System :: OS Independent
Classifier: Programming Language :: Python :: 3
Classifier: Programming Language :: Python :: 3.8
Classifier: Programming Language :: Python :: 3.9
Classifier: Programming Language :: Python :: 3.10
Classifier: Programming Language :: Python :: 3.11
Classifier: Programming Language :: Python :: 3.12
Classifier: Programming Language :: Python :: 3.13
Classifier: Topic :: Software Development :: Libraries
Classifier: Topic :: Software Development :: Libraries :: Python Modules
Requires-Dist: django (>=3.2,<5.2)
Project-URL: Repository, https://github.com/mathewpower/django-rename-table
Project-URL: documentation, https://github.com/mathewpower/django-rename-table#readme
Project-URL: issues, https://github.com/mathewpower/django-rename-table/issues
